aspose_barcode_cloud/__init__.py
aspose_barcode_cloud/api_client.py
aspose_barcode_cloud/api_response.py
aspose_barcode_cloud/configuration.py
aspose_barcode_cloud/exceptions.py
aspose_barcode_cloud/py.typed
aspose_barcode_cloud/rest.py
aspose_barcode_cloud/api/__init__.py
aspose_barcode_cloud/api/generate_api.py
aspose_barcode_cloud/api/recognize_api.py
aspose_barcode_cloud/api/scan_api.py
aspose_barcode_cloud/models/__init__.py
aspose_barcode_cloud/models/api_error.py
aspose_barcode_cloud/models/api_error_response.py
aspose_barcode_cloud/models/barcode_image_format.py
aspose_barcode_cloud/models/barcode_image_params.py
aspose_barcode_cloud/models/barcode_response.py
aspose_barcode_cloud/models/barcode_response_list.py
aspose_barcode_cloud/models/code_location.py
aspose_barcode_cloud/models/decode_barcode_type.py
aspose_barcode_cloud/models/encode_barcode_type.py
aspose_barcode_cloud/models/encode_data.py
aspose_barcode_cloud/models/encode_data_type.py
aspose_barcode_cloud/models/generate_params.py
aspose_barcode_cloud/models/graphics_unit.py
aspose_barcode_cloud/models/recognition_image_kind.py
aspose_barcode_cloud/models/recognition_mode.py
aspose_barcode_cloud/models/recognize_base64_request.py
aspose_barcode_cloud/models/region_point.py
aspose_barcode_cloud/models/scan_base64_request.py
aspose_barcode_cloud-26.1.0.dist-info/licenses/LICENSE
aspose_barcode_cloud-26.1.0.dist-info/METADATA
aspose_barcode_cloud-26.1.0.dist-info/WHEEL
aspose_barcode_cloud-26.1.0.dist-info/top_level.txt
aspose_barcode_cloud-26.1.0.dist-info/RECORD
