Metadata-Version: 2.4
Name: aspose-barcode-cloud
Version: 26.1.0
Summary: Aspose.BarCode.Cloud v4.0 Specification
Home-page: https://github.com/aspose-barcode-cloud/aspose-barcode-cloud-python
Author: Aspose Barcode Cloud
License: MIT
Project-URL: Source With Tests, https://github.com/aspose-barcode-cloud/aspose-barcode-cloud-python
Project-URL: Website, https://www.aspose.cloud
Project-URL: Product Home, https://products.aspose.cloud/barcode/
Project-URL: Documentation, https://docs.aspose.cloud/barcode/
Project-URL: Free Support Forum, https://forum.aspose.cloud/c/barcode
Project-URL: Paid Support Helpdesk, https://helpdesk.aspose.cloud/
Project-URL: Blog, https://blog.aspose.cloud/categories/aspose.barcode-cloud-product-family/
Keywords: Barcode-Scan,QR,DataMatrix,Barcode,AustraliaPost,VIN,MSI,Aztec,ISBN,OPC,Postnet,2D-Barcode,EAN13,ISSN,PZN,SingaporePost,Symbology,UPCA,UPCE,1D-Barcode,Code11,Code128,Code32,Codetext,DotCode,EAN14,EAN8,GS1DataMatrix,Interleaved2of5,ISMN,MaxiCode,OneCode,Pdf417,Pharmacode,Postal-Barcode,RM4SCC,SCC14,SSCC18,Code39Standard,GS1QR,MacroPdf417,JPEG,TIFF,PNG,BMP,GIF,EXIF,EMF,SVG,Aspose.BarCode,Aspose.BarCode-Cloud,Aspose.Total-Cloud,Cloud,REST,API,Generate-Barcode,Barcode-Generation,Barcode-Fo
Classifier: Development Status :: 5 - Production/Stable
Classifier: Intended Audience :: Developers
Classifier: Topic :: Software Development
Classifier: License :: OSI Approved :: MIT License
Classifier: Operating System :: OS Independent
Classifier: Programming Language :: Python :: 3
Classifier: Programming Language :: Python :: 3.9
Classifier: Programming Language :: Python :: 3.10
Classifier: Programming Language :: Python :: 3.11
Classifier: Programming Language :: Python :: 3.12
Classifier: Programming Language :: Python :: 3.13
Classifier: Programming Language :: Python :: 3.14
License-File: LICENSE
Requires-Dist: certifi>=2024.7.4
Requires-Dist: python-dateutil>=2.1
Requires-Dist: urllib3<3.0,>=2.5.0
Dynamic: author
Dynamic: classifier
Dynamic: description
Dynamic: description-content-type
Dynamic: home-page
Dynamic: keywords
Dynamic: license
Dynamic: license-file
Dynamic: project-url
Dynamic: requires-dist
Dynamic: summary
